oceansoundscape/__init__.py
oceansoundscape/raven/__init__.py
oceansoundscape/raven/parser.py
oceansoundscape/spectrogram/__init__.py
oceansoundscape/spectrogram/colormap.py
oceansoundscape/spectrogram/conf.py
oceansoundscape/spectrogram/denoise.py
oceansoundscape/spectrogram/signal.py
oceansoundscape/spectrogram/utils.py
oceansoundscape/testdata/MARS-20150910T000000Z-2kHz.wav
oceansoundscape/testdata/MARS-20150910T000000Z-2kHz.wav.Table01.txt
oceansoundscape/testdata/MARS-20160521T000000Z-2kHz.wav.Table01.txt
oceansoundscape/testdata/MARS-20160617T000000Z-2kHz.wav.Table01.txt
oceansoundscape/testdata/MARS-20170415T000000Z-2kHz.wav.Table01.txt
oceansoundscape/testdata/MARS-20190728T000000Z-2kHz.wav.Table01.txt
oceansoundscape/testdata/MARS-20201109T000000Z-2kHz.wav.Table01.txt
oceansoundscape/testdata/__init__.py
oceansoundscape/testdata/blueDBLEDval/MARS-20150808T000000Z-2kHz.Band.Limited.Energy.Detector.selections.txt
oceansoundscape/testdata/blueDBLEDval/MARS-20150809T000000Z-2kHz.Band.Limited.Energy.Detector.selections.txt
oceansoundscape/testdata/blueDBLEDval/MARS-20150902T000000Z-2kHz.Band.Limited.Energy.Detector.selections.txt
oceansoundscape/testdata/blueDBLEDval/MARS-20150903T000000Z-2kHz.Band.Limited.Energy.Detector.selections.txt
oceansoundscape/testdata/blueDBLEDval/MARS-20151025T000000Z-2kHz.Band.Limited.Energy.Detector.selections.txt
oceansoundscape/testdata/blueDBLEDval/MARS-20151026T000000Z-2kHz.Band.Limited.Energy.Detector.selections.txt
oceansoundscape/testdata/blueDBLEDval/MARS-20151129T000000Z-2kHz.Band.Limited.Energy.Detector.selections.txt
oceansoundscape/testdata/blueDBLEDval/MARS-20151130T000000Z-2kHz.Band.Limited.Energy.Detector.selections.txt
oceansoundscape/testdata/blueDBLEDval/MARS-20151215T000000Z-2kHz.Band.Limited.Energy.Detector.selections.txt
oceansoundscape/testdata/blueDBLEDval/MARS-20151216T000000Z-2kHz.Band.Limited.Energy.Detector.selections.txt
oceansoundscape-2.0.1.dist-info/LICENSE
oceansoundscape-2.0.1.dist-info/METADATA
oceansoundscape-2.0.1.dist-info/WHEEL
oceansoundscape-2.0.1.dist-info/RECORD
