Metadata-Version: 2.1
Name: oceansoundscape
Version: 2.0.1
Summary: A python package for analyzing ocean acoustic data. 
Home-page: https://github.com/mbari-org/oceansoundscape
License: GPL3
Keywords: ocean,acoustic,soundscape,analysis
Author: Danelle Cline
Author-email: dcline@mbari.org
Requires-Python: >=3.9,<=3.11.0
Classifier: Development Status :: 1 - Planning
Classifier: Environment :: Console
Classifier: Intended Audience :: Developers
Classifier: Intended Audience :: Science/Research
Classifier: License :: OSI Approved :: GNU General Public License (GPL)
Classifier: License :: Other/Proprietary License
Classifier: Operating System :: OS Independent
Classifier: Programming Language :: Python :: 3
Classifier: Programming Language :: Python :: 3.9
Classifier: Programming Language :: Python :: 3.10
Classifier: Programming Language :: Python :: 3.11
Requires-Dist: h5py (>=3.8.0,<4.0.0)
Requires-Dist: librosa (>=0.9.1,<0.10.0)
Requires-Dist: matplotlib (>=3.6.3,<4.0.0)
Requires-Dist: numpy (==1.23.5)
Requires-Dist: opencv-python-headless (>=4.7.0,<5.0.0)
Requires-Dist: pandas (>=1.5.3,<2.0.0)
Requires-Dist: scikit-learn (>=1.5.0,<2.0.0)
Requires-Dist: scipy (>=1.10.0,<2.0.0)
Requires-Dist: soundfile (>=0.10.3.post1,<0.11.0)
Project-URL: Repository, https://github.com/mbari-org/oceansoundscape
